errorship/__init__.py
errorship/excepthook.py
errorship/handler.py
errorship/http.py
errorship/initialize.py
errorship/py_version.py
errorship/sock.py
errorship-0.0.7b0.dist-info/LICENSE
errorship-0.0.7b0.dist-info/METADATA
errorship-0.0.7b0.dist-info/WHEEL
errorship-0.0.7b0.dist-info/top_level.txt
errorship-0.0.7b0.dist-info/RECORD
