Metadata-Version: 2.1
Name: errorship
Version: 0.0.7b0
Summary: Send exceptions to datadog.
Home-page: https://errorship.com/
Author: errorship.com
Author-email: errorship.com@gmail.com
License: https://gitlab.com/errorship/errorship_python/-/blob/master/LICENSE
Keywords: errorship,errors,exceptions,datadog,error tracker,error tracking
Platform: UNKNOWN
Classifier: Development Status :: 4 - Beta
Classifier: Intended Audience :: Developers
Classifier: Intended Audience :: Information Technology
Classifier: Intended Audience :: System Administrators
Classifier: License :: Other/Proprietary License
Classifier: Natural Language :: English
Classifier: Operating System :: OS Independent
Classifier: Programming Language :: Python :: 2
Classifier: Programming Language :: Python :: 3
Classifier: Programming Language :: Python
Classifier: Topic :: Software Development :: Build Tools
Classifier: Topic :: Internet :: WWW/HTTP
Classifier: Topic :: Security
Classifier: Topic :: System :: Installation/Setup
Classifier: Topic :: System :: Networking
Classifier: Topic :: System :: Systems Administration
Classifier: Topic :: Utilities
Provides-Extra: dev
Requires-Dist: Sphinx (==2.2.2) ; extra == 'dev'
Requires-Dist: pypandoc (==1.5) ; extra == 'dev'
Requires-Dist: sphinx-autodoc-typehints (==1.10.3) ; extra == 'dev'
Requires-Dist: sphinx-rtd-theme (==0.4.3) ; extra == 'dev'
Requires-Dist: twine (==3.1.1) ; extra == 'dev'
Requires-Dist: wheel (==0.33.6) ; extra == 'dev'
Provides-Extra: examples
Requires-Dist: django (==1.11) ; extra == 'examples'
Requires-Dist: flask (==1.1) ; extra == 'examples'
Provides-Extra: test_py2
Requires-Dist: coverage ; extra == 'test_py2'
Requires-Dist: flake8 ; extra == 'test_py2'
Requires-Dist: mock ; extra == 'test_py2'
Requires-Dist: pylint ; extra == 'test_py2'
Provides-Extra: test_py3
Requires-Dist: bandit ; extra == 'test_py3'
Requires-Dist: black ; extra == 'test_py3'
Requires-Dist: coverage ; extra == 'test_py3'
Requires-Dist: flake8 ; extra == 'test_py3'
Requires-Dist: mock ; extra == 'test_py3'
Requires-Dist: mypy ; extra == 'test_py3'
Requires-Dist: pylint ; extra == 'test_py3'
Requires-Dist: pytype ; extra == 'test_py3'
